[
  {
    "epoch": 1,
    "loss": 161540518.9827306
  },
  {
    "epoch": 2,
    "loss": 161221042.3105445
  },
  {
    "epoch": 3,
    "loss": 160762304.17777327
  },
  {
    "epoch": 4,
    "loss": 160166558.18742383
  },
  {
    "epoch": 5,
    "loss": 159435471.46901667
  },
  {
    "epoch": 6,
    "loss": 158570730.64485982
  },
  {
    "epoch": 7,
    "loss": 157574247.0405323
  },
  {
    "epoch": 8,
    "loss": 156448149.6908777
  },
  {
    "epoch": 9,
    "loss": 155194786.70997563
  },
  {
    "epoch": 10,
    "loss": 153816804.78941488
  }
]